{
  "main": {
    "id": "ecc8bafb8e55487d",
    "type": "split",
    "children": [
      {
        "id": "4af96b949524e85e",
        "type": "tabs",
        "children": [
          {
            "id": "17a224d003ab85c7",
            "type": "leaf",
            "state": {
              "type": "markdown",
              "state": {
                "file": "Camada de acesso e Tecnologia de borda.md",
                "mode": "source",
                "source": false
              },
              "icon": "lucide-file",
              "title": "Camada de acesso e Tecnologia de borda"
            }
          }
        ]
      }
    ],
    "direction": "vertical"
  },
  "left": {
    "id": "cf6a41618ee8895e",
    "type": "split",
    "children": [
      {
        "id": "d98e2c3375cead81",
        "type": "tabs",
        "children": [
          {
            "id": "2556665b1790a67b",
            "type": "leaf",
            "state": {
              "type": "file-explorer",
              "state": {
                "sortOrder": "alphabetical",
                "autoReveal": false
              },
              "icon": "lucide-folder-closed",
              "title": "Files"
            }
          },
          {
            "id": "bad8794a2ead5f9a",
            "type": "leaf",
            "state": {
              "type": "search",
              "state": {
                "query": "",
                "matchingCase": false,
                "explainSearch": false,
                "collapseAll": false,
                "extraContext": false,
                "sortOrder": "alphabetical"
              },
              "icon": "lucide-search",
              "title": "Search"
            }
          },
          {
            "id": "b5ccb69ee5728133",
            "type": "leaf",
            "state": {
              "type": "bookmarks",
              "state": {},
              "icon": "lucide-bookmark",
              "title": "Bookmarks"
            }
          }
        ]
      }
    ],
    "direction": "horizontal",
    "width": 200,
    "collapsed": true
  },
  "right": {
    "id": "f3822a651fc386ce",
    "type": "split",
    "children": [
      {
        "id": "635e352d460d01b6",
        "type": "tabs",
        "children": [
          {
            "id": "76b69cb57975fe0d",
            "type": "leaf",
            "state": {
              "type": "backlink",
              "state": {
                "file": "Otimização e Programação Linear/Introdutória.md",
                "collapseAll": false,
                "extraContext": false,
                "sortOrder": "alphabetical",
                "showSearch": false,
                "searchQuery": "",
                "backlinkCollapsed": false,
                "unlinkedCollapsed": true
              },
              "icon": "links-coming-in",
              "title": "Backlinks for Introdutória"
            }
          },
          {
            "id": "7119238f34351031",
            "type": "leaf",
            "state": {
              "type": "outgoing-link",
              "state": {
                "file": "Otimização e Programação Linear/Introdutória.md",
                "linksCollapsed": false,
                "unlinkedCollapsed": true
              },
              "icon": "links-going-out",
              "title": "Outgoing links from Introdutória"
            }
          },
          {
            "id": "f77ce401e1c40f17",
            "type": "leaf",
            "state": {
              "type": "tag",
              "state": {
                "sortOrder": "frequency",
                "useHierarchy": true,
                "showSearch": false,
                "searchQuery": ""
              },
              "icon": "lucide-tags",
              "title": "Tags"
            }
          },
          {
            "id": "69639d3000bbac7f",
            "type": "leaf",
            "state": {
              "type": "outline",
              "state": {
                "file": "Otimização e Programação Linear/Introdutória.md",
                "followCursor": false,
                "showSearch": false,
                "searchQuery": ""
              },
              "icon": "lucide-list",
              "title": "Outline of Introdutória"
            }
          }
        ]
      }
    ],
    "direction": "horizontal",
    "width": 300,
    "collapsed": true
  },
  "left-ribbon": {
    "hiddenItems": {
      "switcher:Open quick switcher": false,
      "graph:Open graph view": false,
      "canvas:Create new canvas": false,
      "daily-notes:Open today's daily note": false,
      "templates:Insert template": false,
      "command-palette:Open command palette": false
    }
  },
  "active": "17a224d003ab85c7",
  "lastOpenFiles": [
    "Camada de acesso e Tecnologia de borda.md",
    "Otimização e Programação Linear/TSP.md",
    "Avaliação de Desempenho/Aula 03 - Distribuição exponencial.md",
    "Minimal Colab.md",
    "Avaliação de Desempenho/Métricas de desempenho.md",
    "Avaliação de Desempenho/Introdutória.md",
    "Avaliação de Desempenho/O que é avaliação de desempenho em computação.md",
    "Avaliação de Desempenho/Aula 02 - Classificação de Redes de Filas.md",
    "Otimização e Programação Linear/Convex Optimization.md",
    "Welcome.md",
    "Teste.md",
    "IoT/Segurança.md",
    "IoT/Explorando o paper.md",
    "IoT/RFID.md",
    "IoT/Apresentação da disciplina (segunda metade).md",
    "Otimização e Programação Linear/AMPL.md",
    "Otimização e Programação Linear/SimplexCanalizado - Colab.md",
    "Otimização e Programação Linear/Introdutória.md",
    "IoT",
    "Pasted image 20250424101647.png",
    "Pasted image 20250424101521.png",
    "Pasted image 20250424101350.png",
    "Pasted image 20250424101343.png",
    "Pasted image 20250424095657.png",
    "Pasted image 20250424095444.png",
    "Pasted image 20250424095024.png",
    "Pasted image 20250424095015.png",
    "Avaliação de Desempenho",
    "Otimização e Programação Linear"
  ]
}